Workbook

Sheet Phase 1-  Budget by Month
A1: Competition Sensitive Information – Distribution with Agreements Officer’s authorization only | B1: Phase 1 | BD1: TOTAL PROPOSED HOURS | BE1: TOTAL PROPOSED AMOUNT
B2: Month 1 (see Note 8 below) | E2: Month 2 | H2: Month 3 | K2: Month 4 | N2: Month 5 | Q2: Month 6 | T2: Month 7 | W2: Month 8 | Z2: Month 9 | AC2: Month 10 | AF2: Month 11 | AI2: Month 12 | AL2: Month 13 | AO2: Month 14 | AR2: Month 15 | AU2: Month 16 | AX2: Month 17 | BA2: Month 18
A3: DIRECT LABOR (List each category separately) | B3: HOURS | C3: RATE | D3: AMOUNT | E3: HOURS | F3: RATE | G3: AMOUNT | H3: HOURS | I3: RATE | J3: AMOUNT | K3: HOURS | L3: RATE | M3: AMOUNT | N3: HOURS | O3: RATE | P3: AMOUNT | Q3: HOURS | R3: RATE | S3: AMOUNT | T3: HOURS | U3: RATE | V3: AMOUNT | W3: HOURS | X3: RATE | Y3: AMOUNT | Z3: HOURS | AA3: RATE | AB3: AMOUNT | AC3: HOURS | AD3: RATE | AE3: AMOUNT | AF3: HOURS | AG3: RATE | AH3: AMOUNT | AI3: HOURS | AJ3: RATE | AK3: AMOUNT | AL3: HOURS | AM3: RATE | AN3: AMOUNT | AO3: HOURS | AP3: RATE | AQ3: AMOUNT | AR3: HOURS | AS3: RATE | AT3: AMOUNT | AU3: HOURS | AV3: RATE | AW3: AMOUNT | AX3: HOURS | AY3: RATE | AZ3: AMOUNT | BA3: HOURS | BB3: RATE | BC3: AMOUNT
B4: 0 | D4: =B4*C4 -> 0 | E4: 0 | G4: =E4*F4 -> 0 | H4: 0 | J4: =H4*I4 -> 0 | K4: 0 | M4: =K4*L4 -> 0 | N4: 0 | P4: =N4*O4 -> 0 | Q4: 0 | S4: =Q4*R4 -> 0 | T4: 0 | V4: =T4*U4 -> 0 | W4: 0 | Y4: =W4*X4 -> 0 | Z4: 0 | AB4: =Z4*AA4 -> 0 | AC4: 0 | AE4: =AC4*AD4 -> 0 | AF4: 0 | AH4: =AF4*AG4 -> 0 | AI4: 0 | AK4: =AI4*AJ4 -> 0 | AL4: 0 | AN4: =AL4*AM4 -> 0 | AO4: 0 | AQ4: =AO4*AP4 -> 0 | AR4: 0 | AT4: =AR4*AS4 -> 0 | AU4: 0 | AW4: =AU4*AV4 -> 0 | AX4: 0 | AZ4: =AX4*AY4 -> 0 | BA4: 0 | BC4: =BA4*BB4 -> 0 | BD4: =SUM(B4,E4,H4,K4,N4,Q4,T4,W4,Z4,AC4,AF4,AI4,AL4,AO4,AR4,AU4,AX4,BA4) -> 0 | BE4: =SUM(D4,G4,J4,M4,P4,S4,V4,Y4,AB4,AE4,AH4,AK4,AN4,AQ4,AT4,AW4,AZ4,BC4) -> 0
B5: 0 | D5: =B5*C5 -> 0 | E5: 0 | G5: =E5*F5 -> 0 | H5: 0 | J5: =H5*I5 -> 0 | K5: 0 | M5: =K5*L5 -> 0 | N5: 0 | P5: =N5*O5 -> 0 | Q5: 0 | S5: =Q5*R5 -> 0 | T5: 0 | V5: =T5*U5 -> 0 | W5: 0 | Y5: =W5*X5 -> 0 | Z5: 0 | AB5: =Z5*AA5 -> 0 | AC5: 0 | AE5: =AC5*AD5 -> 0 | AF5: 0 | AH5: =AF5*AG5 -> 0 | AI5: 0 | AK5: =AI5*AJ5 -> 0 | AL5: 0 | AN5: =AL5*AM5 -> 0 | AO5: 0 | AQ5: =AO5*AP5 -> 0 | AR5: 0 | AT5: =AR5*AS5 -> 0 | AU5: 0 | AW5: =AU5*AV5 -> 0 | AX5: 0 | AZ5: =AX5*AY5 -> 0 | BA5: 0 | BC5: =BA5*BB5 -> 0 | BD5: =SUM(B5,E5,H5,K5,N5,Q5,T5,W5,Z5,AC5,AF5,AI5,AL5,AO5,AR5,AU5,AX5,BA5) -> 0 | BE5: =SUM(D5,G5,J5,M5,P5,S5,V5,Y5,AB5,AE5,AH5,AK5,AN5,AQ5,AT5,AW5,AZ5,BC5) -> 0
B6: 0 | D6: =B6*C6 -> 0 | E6: 0 | G6: =E6*F6 -> 0 | H6: 0 | J6: =H6*I6 -> 0 | K6: 0 | M6: =K6*L6 -> 0 | N6: 0 | P6: =N6*O6 -> 0 | Q6: 0 | S6: =Q6*R6 -> 0 | T6: 0 | V6: =T6*U6 -> 0 | W6: 0 | Y6: =W6*X6 -> 0 | Z6: 0 | AB6: =Z6*AA6 -> 0 | AC6: 0 | AE6: =AC6*AD6 -> 0 | AF6: 0 | AH6: =AF6*AG6 -> 0 | AI6: 0 | AK6: =AI6*AJ6 -> 0 | AL6: 0 | AN6: =AL6*AM6 -> 0 | AO6: 0 | AQ6: =AO6*AP6 -> 0 | AR6: 0 | AT6: =AR6*AS6 -> 0 | AU6: 0 | AW6: =AU6*AV6 -> 0 | AX6: 0 | AZ6: =AX6*AY6 -> 0 | BA6: 0 | BC6: =BA6*BB6 -> 0 | BD6: =SUM(B6,E6,H6,K6,N6,Q6,T6,W6,Z6,AC6,AF6,AI6,AL6,AO6,AR6,AU6,AX6,BA6) -> 0 | BE6: =SUM(D6,G6,J6,M6,P6,S6,V6,Y6,AB6,AE6,AH6,AK6,AN6,AQ6,AT6,AW6,AZ6,BC6) -> 0
B7: 0 | D7: =B7*C7 -> 0 | E7: 0 | G7: =E7*F7 -> 0 | H7: 0 | J7: =H7*I7 -> 0 | K7: 0 | M7: =K7*L7 -> 0 | N7: 0 | P7: =N7*O7 -> 0 | Q7: 0 | S7: =Q7*R7 -> 0 | T7: 0 | V7: =T7*U7 -> 0 | W7: 0 | Y7: =W7*X7 -> 0 | Z7: 0 | AB7: =Z7*AA7 -> 0 | AC7: 0 | AE7: =AC7*AD7 -> 0 | AF7: 0 | AH7: =AF7*AG7 -> 0 | AI7: 0 | AK7: =AI7*AJ7 -> 0 | AL7: 0 | AN7: =AL7*AM7 -> 0 | AO7: 0 | AQ7: =AO7*AP7 -> 0 | AR7: 0 | AT7: =AR7*AS7 -> 0 | AU7: 0 | AW7: =AU7*AV7 -> 0 | AX7: 0 | AZ7: =AX7*AY7 -> 0 | BA7: 0 | BC7: =BA7*BB7 -> 0 | BD7: =SUM(B7,E7,H7,K7,N7,Q7,T7,W7,Z7,AC7,AF7,AI7,AL7,AO7,AR7,AU7,AX7,BA7) -> 0 | BE7: =SUM(D7,G7,J7,M7,P7,S7,V7,Y7,AB7,AE7,AH7,AK7,AN7,AQ7,AT7,AW7,AZ7,BC7) -> 0
B8: 0 | D8: =B8*C8 -> 0 | E8: 0 | G8: =E8*F8 -> 0 | H8: 0 | J8: =H8*I8 -> 0 | K8: 0 | M8: =K8*L8 -> 0 | N8: 0 | P8: =N8*O8 -> 0 | Q8: 0 | S8: =Q8*R8 -> 0 | T8: 0 | V8: =T8*U8 -> 0 | W8: 0 | Y8: =W8*X8 -> 0 | Z8: 0 | AB8: =Z8*AA8 -> 0 | AC8: 0 | AE8: =AC8*AD8 -> 0 | AF8: 0 | AH8: =AF8*AG8 -> 0 | AI8: 0 | AK8: =AI8*AJ8 -> 0 | AL8: 0 | AN8: =AL8*AM8 -> 0 | AO8: 0 | AQ8: =AO8*AP8 -> 0 | AR8: 0 | AT8: =AR8*AS8 -> 0 | AU8: 0 | AW8: =AU8*AV8 -> 0 | AX8: 0 | AZ8: =AX8*AY8 -> 0 | BA8: 0 | BC8: =BA8*BB8 -> 0 | BD8: =SUM(B8,E8,H8,K8,N8,Q8,T8,W8,Z8,AC8,AF8,AI8,AL8,AO8,AR8,AU8,AX8,BA8) -> 0 | BE8: =SUM(D8,G8,J8,M8,P8,S8,V8,Y8,AB8,AE8,AH8,AK8,AN8,AQ8,AT8,AW8,AZ8,BC8) -> 0
B9: 0 | D9: =B9*C9 -> 0 | E9: 0 | G9: =E9*F9 -> 0 | H9: 0 | J9: =H9*I9 -> 0 | K9: 0 | M9: =K9*L9 -> 0 | N9: 0 | P9: =N9*O9 -> 0 | Q9: 0 | S9: =Q9*R9 -> 0 | T9: 0 | V9: =T9*U9 -> 0 | W9: 0 | Y9: =W9*X9 -> 0 | Z9: 0 | AB9: =Z9*AA9 -> 0 | AC9: 0 | AE9: =AC9*AD9 -> 0 | AF9: 0 | AH9: =AF9*AG9 -> 0 | AI9: 0 | AK9: =AI9*AJ9 -> 0 | AL9: 0 | AN9: =AL9*AM9 -> 0 | AO9: 0 | AQ9: =AO9*AP9 -> 0 | AR9: 0 | AT9: =AR9*AS9 -> 0 | AU9: 0 | AW9: =AU9*AV9 -> 0 | AX9: 0 | AZ9: =AX9*AY9 -> 0 | BA9: 0 | BC9: =BA9*BB9 -> 0 | BD9: =SUM(B9,E9,H9,K9,N9,Q9,T9,W9,Z9,AC9,AF9,AI9,AL9,AO9,AR9,AU9,AX9,BA9) -> 0 | BE9: =SUM(D9,G9,J9,M9,P9,S9,V9,Y9,AB9,AE9,AH9,AK9,AN9,AQ9,AT9,AW9,AZ9,BC9) -> 0
A10: SUBTOTAL (all direct labor costs) | B10: =SUM(B4:B9) -> 0 | D10: =SUM(D4:D9) -> 0 | E10: =SUM(E4:E9) -> 0 | G10: =SUM(G4:G9) -> 0 | H10: =SUM(H4:H9) -> 0 | J10: =SUM(J4:J9) -> 0 | K10: =SUM(K4:K9) -> 0 | M10: =SUM(M4:M9) -> 0 | N10: =SUM(N4:N9) -> 0 | P10: =SUM(P4:P9) -> 0 | Q10: =SUM(Q4:Q9) -> 0 | S10: =SUM(S4:S9) -> 0 | T10: =SUM(T4:T9) -> 0 | V10: =SUM(V4:V9) -> 0 | W10: =SUM(W4:W9) -> 0 | Y10: =SUM(Y4:Y9) -> 0 | Z10: =SUM(Z4:Z9) -> 0 | AB10: =SUM(AB4:AB9) -> 0 | AC10: =SUM(AC4:AC9) -> 0 | AE10: =SUM(AE4:AE9) -> 0 | AF10: =SUM(AF4:AF9) -> 0 | AH10: =SUM(AH4:AH9) -> 0 | AI10: =SUM(AI4:AI9) -> 0 | AK10: =SUM(AK4:AK9) -> 0 | AL10: =SUM(AL4:AL9) -> 0 | AN10: =SUM(AN4:AN9) -> 0 | AO10: =SUM(AO4:AO9) -> 0 | AQ10: =SUM(AQ4:AQ9) -> 0 | AR10: =SUM(AR4:AR9) -> 0 | AT10: =SUM(AT4:AT9) -> 0 | AU10: =SUM(AU4:AU9) -> 0 | AW10: =SUM(AW4:AW9) -> 0 | AX10: =SUM(AX4:AX9) -> 0 | AZ10: =SUM(AZ4:AZ9) -> 0 | BA10: =SUM(BA4:BA9) -> 0 | BC10: =SUM(BC4:BC9) -> 0 | BD10: =SUM(B10,E10,H10,K10,N10,Q10,T10,W10,Z10,AC10,AF10,AI10,AL10,AO10,AR10,AU10,AX10,BA10) -> 0 | BE10: =SUM(D10,G10,J10,M10,P10,S10,V10,Y10,AB10,AE10,AH10,AK10,AN10,AQ10,AT10,AW10,AZ10,BC10) -> 0
A11: SUBCONTRACTOR(S) & CONSULTANT(S) (List each separately) | D11: 0 | G11: 0 | J11: 0 | M11: 0 | P11: 0 | S11: 0 | V11: 0 | Y11: 0 | AB11: 0 | AE11: 0 | AH11: 0 | AK11: 0 | AN11: 0 | AQ11: 0 | AT11: 0 | AW11: 0 | AZ11: 0 | BC11: 0 | BD11: =SUM(B11,E11,H11,K11,N11,Q11,T11,W11,Z11,AC11,AF11,AI11,AL11,AO11,AR11,AU11,AX11,BA11) -> 0 | BE11: =SUM(D11,G11,J11,M11,P11,S11,V11,Y11,AB11,AE11,AH11,AK11,AN11,AQ11,AT11,AW11,AZ11,BC11) -> 0
D12: 0 | G12: 0 | J12: 0 | M12: 0 | P12: 0 | S12: 0 | V12: 0 | Y12: 0 | AB12: 0 | AE12: 0 | AH12: 0 | AK12: 0 | AN12: 0 | AQ12: 0 | AT12: 0 | AW12: 0 | AZ12: 0 | BC12: 0 | BD12: =SUM(B12,E12,H12,K12,N12,Q12,T12,W12,Z12,AC12,AF12,AI12,AL12,AO12,AR12,AU12,AX12,BA12) -> 0 | BE12: =SUM(D12,G12,J12,M12,P12,S12,V12,Y12,AB12,AE12,AH12,AK12,AN12,AQ12,AT12,AW12,AZ12,BC12) -> 0
D13: 0 | G13: 0 | J13: 0 | M13: 0 | P13: 0 | S13: 0 | V13: 0 | Y13: 0 | AB13: 0 | AE13: 0 | AH13: 0 | AK13: 0 | AN13: 0 | AQ13: 0 | AT13: 0 | AW13: 0 | AZ13: 0 | BC13: 0 | BD13: =SUM(B13,E13,H13,K13,N13,Q13,T13,W13,Z13,AC13,AF13,AI13,AL13,AO13,AR13,AU13,AX13,BA13) -> 0 | BE13: =SUM(D13,G13,J13,M13,P13,S13,V13,Y13,AB13,AE13,AH13,AK13,AN13,AQ13,AT13,AW13,AZ13,BC13) -> 0
D14: 0 | G14: 0 | J14: 0 | M14: 0 | P14: 0 | S14: 0 | V14: 0 | Y14: 0 | AB14: 0 | AE14: 0 | AH14: 0 | AK14: 0 | AN14: 0 | AQ14: 0 | AT14: 0 | AW14: 0 | AZ14: 0 | BC14: 0 | BD14: =SUM(B14,E14,H14,K14,N14,Q14,T14,W14,Z14,AC14,AF14,AI14,AL14,AO14,AR14,AU14,AX14,BA14) -> 0 | BE14: =SUM(D14,G14,J14,M14,P14,S14,V14,Y14,AB14,AE14,AH14,AK14,AN14,AQ14,AT14,AW14,AZ14,BC14) -> 0
A15: SUBTOTAL (all subcontractor/consultant costs) | B15: =SUM(B11:B14) -> 0 | D15: =SUM(D11:D14) -> 0 | E15: =SUM(E11:E14) -> 0 | G15: =SUM(G11:G14) -> 0 | H15: =SUM(H11:H14) -> 0 | J15: =SUM(J11:J14) -> 0 | K15: =SUM(K11:K14) -> 0 | M15: =SUM(M11:M14) -> 0 | N15: =SUM(N11:N14) -> 0 | P15: =SUM(P11:P14) -> 0 | Q15: =SUM(Q11:Q14) -> 0 | S15: =SUM(S11:S14) -> 0 | T15: =SUM(T11:T14) -> 0 | V15: =SUM(V11:V14) -> 0 | W15: =SUM(W11:W14) -> 0 | Y15: =SUM(Y11:Y14) -> 0 | Z15: =SUM(Z11:Z14) -> 0 | AB15: =SUM(AB11:AB14) -> 0 | AC15: =SUM(AC11:AC14) -> 0 | AE15: =SUM(AE11:AE14) -> 0 | AF15: =SUM(AF11:AF14) -> 0 | AH15: =SUM(AH11:AH14) -> 0 | AI15: =SUM(AI11:AI14) -> 0 | AK15: =SUM(AK11:AK14) -> 0 | AL15: =SUM(AL11:AL14) -> 0 | AN15: =SUM(AN11:AN14) -> 0 | AO15: =SUM(AO11:AO14) -> 0 | AQ15: =SUM(AQ11:AQ14) -> 0 | AR15: =SUM(AR11:AR14) -> 0 | AT15: =SUM(AT11:AT14) -> 0 | AU15: =SUM(AU11:AU14) -> 0 | AW15: =SUM(AW11:AW14) -> 0 | AX15: =SUM(AX11:AX14) -> 0 | AZ15: =SUM(AZ11:AZ14) -> 0 | BA15: =SUM(BA11:BA14) -> 0 | BC15: =SUM(BC11:BC14) -> 0 | BD15: =SUM(B15,E15,H15,K15,N15,Q15,T15,W15,Z15,AC15,AF15,AI15,AL15,AO15,AR15,AU15,AX15,BA15) -> 0 | BE15: =SUM(D15,G15,J15,M15,P15,S15,V15,Y15,AB15,AE15,AH15,AK15,AN15,AQ15,AT15,AW15,AZ15,BC15) -> 0
A16: MATERIALS | D16: 0 | G16: 0 | J16: 0 | M16: $ | P16: $ | S16: $ | V16: $ | Y16: $ | AB16: $ | AE16: $ | AH16: $ | AK16: $ | AN16: $ | AQ16: $ | AT16: $ | AW16: $ | AZ16: $ | BC16: $ | BE16: =SUM(D16,G16,J16,M16,P16,S16,V16,Y16,AB16,AE16,AH16,AK16,AN16,AQ16,AT16,AW16,AZ16,BC16) -> 0
A17: EQUIPMENT | D17: 0 | G17: 0 | J17: 0 | M17: 0 | P17: 0 | S17: 0 | V17: 0 | Y17: 0 | AB17: 0 | AE17: 0 | AH17: 0 | AK17: 0 | AN17: 0 | AQ17: 0 | AT17: 0 | AW17: 0 | AZ17: 0 | BC17: 0 | BE17: =SUM(D17,G17,J17,M17,P17,S17,V17,Y17,AB17,AE17,AH17,AK17,AN17,AQ17,AT17,AW17,AZ17,BC17) -> 0
A18: TRAVEL | D18: 0 | G18: 0 | J18: 0 | M18: $ | P18: $ | S18: $ | V18: $ | Y18: $ | AB18: $ | AE18: $ | AH18: $ | AK18: $ | AN18: $ | AQ18: $ | AT18: $ | AW18: $ | AZ18: $ | BC18: $ | BE18: =SUM(D18,G18,J18,M18,P18,S18,V18,Y18,AB18,AE18,AH18,AK18,AN18,AQ18,AT18,AW18,AZ18,BC18) -> 0
A19: OTHER DIRECT COSTS (ODCs) 1 | D19: $ | G19: $ | J19: $ | M19: $ | P19: $ | S19: $ | V19: $ | Y19: $ | AB19: $ | AE19: $ | AH19: $ | AK19: $ | AN19: $ | AQ19: $ | AT19: $ | AW19: $ | AZ19: $ | BC19: $ | BE19: =SUM(D19,G19,J19,M19,P19,S19,V19,Y19,AB19,AE19,AH19,AK19,AN19,AQ19,AT19,AW19,AZ19,BC19) -> 0
A20: OTHER DIRECT COSTS (ODCs) 2 | D20: 0 | G20: 0 | J20: 0 | M20: 0 | P20: 0 | S20: 0 | V20: 0 | Y20: 0 | AB20: 0 | AE20: 0 | AH20: 0 | AK20: 0 | AN20: 0 | AQ20: 0 | AT20: 0 | AW20: 0 | AZ20: 0 | BC20: 0 | BE20: =SUM(D20,G20,J20,M20,P20,S20,V20,Y20,AB20,AE20,AH20,AK20,AN20,AQ20,AT20,AW20,AZ20,BC20) -> 0
A21: OTHER DIRECT COSTS (ODCs) 3 | D21: 0 | G21: 0 | J21: 0 | M21: 0 | P21: 0 | S21: 0 | V21: 0 | Y21: 0 | AB21: 0 | AE21: 0 | AH21: 0 | AK21: 0 | AN21: 0 | AQ21: 0 | AT21: 0 | AW21: 0 | AZ21: 0 | BC21: 0 | BE21: =SUM(D21,G21,J21,M21,P21,S21,V21,Y21,AB21,AE21,AH21,AK21,AN21,AQ21,AT21,AW21,AZ21,BC21) -> 0
A22: SUBTOTAL (M&E, Travel, ODCs) | D22: =SUM(D16:D21) -> 0 | G22: =SUM(G16:G21) -> 0 | J22: =SUM(J16:J21) -> 0 | M22: =SUM(M16:M21) -> 0 | P22: =SUM(P16:P21) -> 0 | S22: =SUM(S16:S21) -> 0 | V22: =SUM(V16:V21) -> 0 | Y22: =SUM(Y16:Y21) -> 0 | AB22: =SUM(AB16:AB21) -> 0 | AE22: =SUM(AE16:AE21) -> 0 | AH22: =SUM(AH16:AH21) -> 0 | AK22: =SUM(AK16:AK21) -> 0 | AN22: =SUM(AN16:AN21) -> 0 | AQ22: =SUM(AQ16:AQ21) -> 0 | AT22: =SUM(AT16:AT21) -> 0 | AW22: =SUM(AW16:AW21) -> 0 | AZ22: =SUM(AZ16:AZ21) -> 0 | BC22: =SUM(BC16:BC21) -> 0 | BE22: =SUM(D22,G22,J22,M22,P22,S22,V22,Y22,AB22,AE22,AH22,AK22,AN22,AQ22,AT22,AW22,AZ22,BC22) -> 0
A23: Profit | D23: 0 | G23: 0 | J23: 0 | M23: 0 | P23: 0 | S23: 0 | V23: 0 | Y23: 0 | AB23: 0 | AE23: 0 | AH23: 0 | AK23: 0 | AN23: 0 | AQ23: 0 | AT23: 0 | AW23: 0 | AZ23: 0 | BC23: 0 | BE23: =SUM(D23,G23,J23,M23,P23,S23,V23,Y23,AB23,AE23,AH23,AK23,AN23,AQ23,AT23,AW23,AZ23,BC23) -> 0
A24: TOTAL PRICE | D24: =SUM(D22,D15,D10,D23) -> 0 | G24: =SUM(G22,G15,G10,G23) -> 0 | J24: =SUM(J22,J15,J10,J23) -> 0 | M24: =SUM(M22,M15,M10,M23) -> 0 | P24: =SUM(P22,P15,P10,P23) -> 0 | S24: =SUM(S22,S15,S10,S23) -> 0 | V24: =SUM(V22,V15,V10,V23) -> 0 | Y24: =SUM(Y22,Y15,Y10,Y23) -> 0 | AB24: =SUM(AB22,AB15,AB10,AB23) -> 0 | AE24: =SUM(AE22,AE15,AE10,AE23) -> 0 | AH24: =SUM(AH22,AH15,AH10,AH23) -> 0 | AK24: =SUM(AK22,AK15,AK10,AK23) -> 0 | AN24: =SUM(AN22,AN15,AN10,AN23) -> 0 | AQ24: =SUM(AQ22,AQ15,AQ10,AQ23) -> 0 | AT24: =SUM(AT22,AT15,AT10,AT23) -> 0 | AW24: =SUM(AW22,AW15,AW10,AW23) -> 0 | AZ24: =SUM(AZ22,AZ15,AZ10,AZ23) -> 0 | BC24: =SUM(BC22,BC15,BC10,BC23) -> 0 | BE24: =SUM(D24,G24,J24,M24,P24,S24,V24,Y24,AB24,AE24,AH24,AK24,AN24,AQ24,AT24,AW24,AZ24,BC24) -> 0
A25: GOVERNMENT SHARE | D25: 0 | G25: 0 | J25: 0 | M25: 0 | P25: 0 | S25: 0 | V25: 0 | Y25: 0 | AB25: 0 | AE25: 0 | AH25: 0 | AK25: 0 | AN25: 0 | AQ25: 0 | AT25: 0 | AW25: 0 | AZ25: 0 | BC25: 0 | BE25: =SUM(D25,G25,J25,M25,P25,S25,V25,Y25,AB25,AE25,AH25,AK25,AN25,AQ25,AT25,AW25,AZ25,BC25) -> 0
A26: RECIPIENT SHARE (if applicable) | D26: =D24-D25 -> 0 | G26: =G24-G25 -> 0 | J26: =J24-J25 -> 0 | M26: =M24-M25 -> 0 | P26: =P24-P25 -> 0 | S26: =S24-S25 -> 0 | V26: =V24-V25 -> 0 | Y26: =Y24-Y25 -> 0 | AB26: =AB24-AB25 -> 0 | AE26: =AE24-AE25 -> 0 | AH26: =AH24-AH25 -> 0 | AK26: =AK24-AK25 -> 0 | AN26: =AN24-AN25 -> 0 | AQ26: =AQ24-AQ25 -> 0 | AT26: =AT24-AT25 -> 0 | AW26: =AW24-AW25 -> 0 | AZ26: =AZ24-AZ25 -> 0 | BC26: =BC24-BC25 -> 0 | BE26: =SUM(D26,G26,J26,M26,P26,S26,V26,Y26,AB26,AE26,AH26,AK26,AN26,AQ26,AT26,AW26,AZ26,BC26) -> 0
B28: Gov't Share | C28: Performer Share | D28: Total Project Cost
A29: Phase 1 Total | B29: =BE25 -> 0 | C29: =BE26 -> 0 | D29: =SUM(B29,C29) -> 0
A31: 1. Proposers are required to add in the Phase 1 cost in the cells above
A32: 2. Phase 1 period of performance are stipulated in the PS and above.
A33: 3. Each submission shall include a separate Price Summary spreadsheet for the Prime and each subcontractor.
A34: 4. Rows can be added to reflect labor categories, subcontractors/consultants, and additional ODCs, as necessary. However, none of the fields currently in the template should be removed, to include formulas.
A35: 5. All proposers, to include Institutions of Higher Education, must include labor hours and associated labor rates for each labor category as stipulated above. Proposers are prohibited from using percent level of effort (LOE) calculations.
A36: 6. Cost elements above should be fully burdened, inclusive of all applicable indirect costs and fee, if applcable. Visibility into indirect rates/costs is not required. Proposers may submit supporting or clarifying information regarding direct and indirect rates in Volume 2.
A37: 7. The pricing for this program must be presented using the 18-month format above. Do not add additional months.

Sheet Phase 2 - Budget by Month
A1: Competition Sensitive Information – Distribution with Agreements Officer’s authorization only | B1: Phase 2 | BD1: TOTAL PROPOSED HOURS | BE1: TOTAL PROPOSED AMOUNT
B2: Month 1 (see Note 8 below) | E2: Month 2 | H2: Month 3 | K2: Month 4 | N2: Month 5 | Q2: Month 6 | T2: Month 7 | W2: Month 8 | Z2: Month 9 | AC2: Month 10 | AF2: Month 11 | AI2: Month 12 | AL2: Month 13 | AO2: Month 14 | AR2: Month 15 | AU2: Month 16 | AX2: Month 17 | BA2: Month 18
A3: DIRECT LABOR (List each category separately) | B3: HOURS | C3: RATE | D3: AMOUNT | E3: HOURS | F3: RATE | G3: AMOUNT | H3: HOURS | I3: RATE | J3: AMOUNT | K3: HOURS | L3: RATE | M3: AMOUNT | N3: HOURS | O3: RATE | P3: AMOUNT | Q3: HOURS | R3: RATE | S3: AMOUNT | T3: HOURS | U3: RATE | V3: AMOUNT | W3: HOURS | X3: RATE | Y3: AMOUNT | Z3: HOURS | AA3: RATE | AB3: AMOUNT | AC3: HOURS | AD3: RATE | AE3: AMOUNT | AF3: HOURS | AG3: RATE | AH3: AMOUNT | AI3: HOURS | AJ3: RATE | AK3: AMOUNT | AL3: HOURS | AM3: RATE | AN3: AMOUNT | AO3: HOURS | AP3: RATE | AQ3: AMOUNT | AR3: HOURS | AS3: RATE | AT3: AMOUNT | AU3: HOURS | AV3: RATE | AW3: AMOUNT | AX3: HOURS | AY3: RATE | AZ3: AMOUNT | BA3: HOURS | BB3: RATE | BC3: AMOUNT
B4: 0 | D4: =B4*C4 -> 0 | E4: 0 | G4: =E4*F4 -> 0 | H4: 0 | J4: =H4*I4 -> 0 | K4: 0 | M4: =K4*L4 -> 0 | N4: 0 | P4: =N4*O4 -> 0 | Q4: 0 | S4: =Q4*R4 -> 0 | T4: 0 | V4: =T4*U4 -> 0 | W4: 0 | Y4: =W4*X4 -> 0 | Z4: 0 | AB4: =Z4*AA4 -> 0 | AC4: 0 | AE4: =AC4*AD4 -> 0 | AF4: 0 | AH4: =AF4*AG4 -> 0 | AI4: 0 | AK4: =AI4*AJ4 -> 0 | AL4: 0 | AN4: =AL4*AM4 -> 0 | AO4: 0 | AQ4: =AO4*AP4 -> 0 | AR4: 0 | AT4: =AR4*AS4 -> 0 | AU4: 0 | AW4: =AU4*AV4 -> 0 | AX4: 0 | AZ4: =AX4*AY4 -> 0 | BA4: 0 | BC4: =BA4*BB4 -> 0 | BD4: =SUM(B4,E4,H4,K4,N4,Q4,T4,W4,Z4,AC4,AF4,AI4,AL4,AO4,AR4,AU4,AX4,BA4) -> 0 | BE4: =SUM(D4,G4,J4,M4,P4,S4,V4,Y4,AB4,AE4,AH4,AK4,AN4,AQ4,AT4,AW4,AZ4,BC4) -> 0
B5: 0 | D5: =B5*C5 -> 0 | E5: 0 | G5: =E5*F5 -> 0 | H5: 0 | J5: =H5*I5 -> 0 | K5: 0 | M5: =K5*L5 -> 0 | N5: 0 | P5: =N5*O5 -> 0 | Q5: 0 | S5: =Q5*R5 -> 0 | T5: 0 | V5: =T5*U5 -> 0 | W5: 0 | Y5: =W5*X5 -> 0 | Z5: 0 | AB5: =Z5*AA5 -> 0 | AC5: 0 | AE5: =AC5*AD5 -> 0 | AF5: 0 | AH5: =AF5*AG5 -> 0 | AI5: 0 | AK5: =AI5*AJ5 -> 0 | AL5: 0 | AN5: =AL5*AM5 -> 0 | AO5: 0 | AQ5: =AO5*AP5 -> 0 | AR5: 0 | AT5: =AR5*AS5 -> 0 | AU5: 0 | AW5: =AU5*AV5 -> 0 | AX5: 0 | AZ5: =AX5*AY5 -> 0 | BA5: 0 | BC5: =BA5*BB5 -> 0 | BD5: =SUM(B5,E5,H5,K5,N5,Q5,T5,W5,Z5,AC5,AF5,AI5,AL5,AO5,AR5,AU5,AX5,BA5) -> 0 | BE5: =SUM(D5,G5,J5,M5,P5,S5,V5,Y5,AB5,AE5,AH5,AK5,AN5,AQ5,AT5,AW5,AZ5,BC5) -> 0
B6: 0 | D6: =B6*C6 -> 0 | E6: 0 | G6: =E6*F6 -> 0 | H6: 0 | J6: =H6*I6 -> 0 | K6: 0 | M6: =K6*L6 -> 0 | N6: 0 | P6: =N6*O6 -> 0 | Q6: 0 | S6: =Q6*R6 -> 0 | T6: 0 | V6: =T6*U6 -> 0 | W6: 0 | Y6: =W6*X6 -> 0 | Z6: 0 | AB6: =Z6*AA6 -> 0 | AC6: 0 | AE6: =AC6*AD6 -> 0 | AF6: 0 | AH6: =AF6*AG6 -> 0 | AI6: 0 | AK6: =AI6*AJ6 -> 0 | AL6: 0 | AN6: =AL6*AM6 -> 0 | AO6: 0 | AQ6: =AO6*AP6 -> 0 | AR6: 0 | AT6: =AR6*AS6 -> 0 | AU6: 0 | AW6: =AU6*AV6 -> 0 | AX6: 0 | AZ6: =AX6*AY6 -> 0 | BA6: 0 | BC6: =BA6*BB6 -> 0 | BD6: =SUM(B6,E6,H6,K6,N6,Q6,T6,W6,Z6,AC6,AF6,AI6,AL6,AO6,AR6,AU6,AX6,BA6) -> 0 | BE6: =SUM(D6,G6,J6,M6,P6,S6,V6,Y6,AB6,AE6,AH6,AK6,AN6,AQ6,AT6,AW6,AZ6,BC6) -> 0
B7: 0 | D7: =B7*C7 -> 0 | E7: 0 | G7: =E7*F7 -> 0 | H7: 0 | J7: =H7*I7 -> 0 | K7: 0 | M7: =K7*L7 -> 0 | N7: 0 | P7: =N7*O7 -> 0 | Q7: 0 | S7: =Q7*R7 -> 0 | T7: 0 | V7: =T7*U7 -> 0 | W7: 0 | Y7: =W7*X7 -> 0 | Z7: 0 | AB7: =Z7*AA7 -> 0 | AC7: 0 | AE7: =AC7*AD7 -> 0 | AF7: 0 | AH7: =AF7*AG7 -> 0 | AI7: 0 | AK7: =AI7*AJ7 -> 0 | AL7: 0 | AN7: =AL7*AM7 -> 0 | AO7: 0 | AQ7: =AO7*AP7 -> 0 | AR7: 0 | AT7: =AR7*AS7 -> 0 | AU7: 0 | AW7: =AU7*AV7 -> 0 | AX7: 0 | AZ7: =AX7*AY7 -> 0 | BA7: 0 | BC7: =BA7*BB7 -> 0 | BD7: =SUM(B7,E7,H7,K7,N7,Q7,T7,W7,Z7,AC7,AF7,AI7,AL7,AO7,AR7,AU7,AX7,BA7) -> 0 | BE7: =SUM(D7,G7,J7,M7,P7,S7,V7,Y7,AB7,AE7,AH7,AK7,AN7,AQ7,AT7,AW7,AZ7,BC7) -> 0
B8: 0 | D8: =B8*C8 -> 0 | E8: 0 | G8: =E8*F8 -> 0 | H8: 0 | J8: =H8*I8 -> 0 | K8: 0 | M8: =K8*L8 -> 0 | N8: 0 | P8: =N8*O8 -> 0 | Q8: 0 | S8: =Q8*R8 -> 0 | T8: 0 | V8: =T8*U8 -> 0 | W8: 0 | Y8: =W8*X8 -> 0 | Z8: 0 | AB8: =Z8*AA8 -> 0 | AC8: 0 | AE8: =AC8*AD8 -> 0 | AF8: 0 | AH8: =AF8*AG8 -> 0 | AI8: 0 | AK8: =AI8*AJ8 -> 0 | AL8: 0 | AN8: =AL8*AM8 -> 0 | AO8: 0 | AQ8: =AO8*AP8 -> 0 | AR8: 0 | AT8: =AR8*AS8 -> 0 | AU8: 0 | AW8: =AU8*AV8 -> 0 | AX8: 0 | AZ8: =AX8*AY8 -> 0 | BA8: 0 | BC8: =BA8*BB8 -> 0 | BD8: =SUM(B8,E8,H8,K8,N8,Q8,T8,W8,Z8,AC8,AF8,AI8,AL8,AO8,AR8,AU8,AX8,BA8) -> 0 | BE8: =SUM(D8,G8,J8,M8,P8,S8,V8,Y8,AB8,AE8,AH8,AK8,AN8,AQ8,AT8,AW8,AZ8,BC8) -> 0
B9: 0 | D9: =B9*C9 -> 0 | E9: 0 | G9: =E9*F9 -> 0 | H9: 0 | J9: =H9*I9 -> 0 | K9: 0 | M9: =K9*L9 -> 0 | N9: 0 | P9: =N9*O9 -> 0 | Q9: 0 | S9: =Q9*R9 -> 0 | T9: 0 | V9: =T9*U9 -> 0 | W9: 0 | Y9: =W9*X9 -> 0 | Z9: 0 | AB9: =Z9*AA9 -> 0 | AC9: 0 | AE9: =AC9*AD9 -> 0 | AF9: 0 | AH9: =AF9*AG9 -> 0 | AI9: 0 | AK9: =AI9*AJ9 -> 0 | AL9: 0 | AN9: =AL9*AM9 -> 0 | AO9: 0 | AQ9: =AO9*AP9 -> 0 | AR9: 0 | AT9: =AR9*AS9 -> 0 | AU9: 0 | AW9: =AU9*AV9 -> 0 | AX9: 0 | AZ9: =AX9*AY9 -> 0 | BA9: 0 | BC9: =BA9*BB9 -> 0 | BD9: =SUM(B9,E9,H9,K9,N9,Q9,T9,W9,Z9,AC9,AF9,AI9,AL9,AO9,AR9,AU9,AX9,BA9) -> 0 | BE9: =SUM(D9,G9,J9,M9,P9,S9,V9,Y9,AB9,AE9,AH9,AK9,AN9,AQ9,AT9,AW9,AZ9,BC9) -> 0
A10: SUBTOTAL (all direct labor costs) | B10: =SUM(B4:B9) -> 0 | D10: =SUM(D4:D9) -> 0 | E10: =SUM(E4:E9) -> 0 | G10: =SUM(G4:G9) -> 0 | H10: =SUM(H4:H9) -> 0 | J10: =SUM(J4:J9) -> 0 | K10: =SUM(K4:K9) -> 0 | M10: =SUM(M4:M9) -> 0 | N10: =SUM(N4:N9) -> 0 | P10: =SUM(P4:P9) -> 0 | Q10: =SUM(Q4:Q9) -> 0 | S10: =SUM(S4:S9) -> 0 | T10: =SUM(T4:T9) -> 0 | V10: =SUM(V4:V9) -> 0 | W10: =SUM(W4:W9) -> 0 | Y10: =SUM(Y4:Y9) -> 0 | Z10: =SUM(Z4:Z9) -> 0 | AB10: =SUM(AB4:AB9) -> 0 | AC10: =SUM(AC4:AC9) -> 0 | AE10: =SUM(AE4:AE9) -> 0 | AF10: =SUM(AF4:AF9) -> 0 | AH10: =SUM(AH4:AH9) -> 0 | AI10: =SUM(AI4:AI9) -> 0 | AK10: =SUM(AK4:AK9) -> 0 | AL10: =SUM(AL4:AL9) -> 0 | AN10: =SUM(AN4:AN9) -> 0 | AO10: =SUM(AO4:AO9) -> 0 | AQ10: =SUM(AQ4:AQ9) -> 0 | AR10: =SUM(AR4:AR9) -> 0 | AT10: =SUM(AT4:AT9) -> 0 | AU10: =SUM(AU4:AU9) -> 0 | AW10: =SUM(AW4:AW9) -> 0 | AX10: =SUM(AX4:AX9) -> 0 | AZ10: =SUM(AZ4:AZ9) -> 0 | BA10: =SUM(BA4:BA9) -> 0 | BC10: =SUM(BC4:BC9) -> 0 | BD10: =SUM(B10,E10,H10,K10,N10,Q10,T10,W10,Z10,AC10,AF10,AI10,AL10,AO10,AR10,AU10,AX10,BA10) -> 0 | BE10: =SUM(D10,G10,J10,M10,P10,S10,V10,Y10,AB10,AE10,AH10,AK10,AN10,AQ10,AT10,AW10,AZ10,BC10) -> 0
A11: SUBCONTRACTOR(S) & CONSULTANT(S) (List each separately) | D11: 0 | G11: 0 | J11: 0 | M11: 0 | P11: 0 | S11: 0 | V11: 0 | Y11: 0 | AB11: 0 | AE11: 0 | AH11: 0 | AK11: 0 | AN11: 0 | AQ11: 0 | AT11: 0 | AW11: 0 | AZ11: 0 | BC11: 0 | BD11: =SUM(B11,E11,H11,K11,N11,Q11,T11,W11,Z11,AC11,AF11,AI11,AL11,AO11,AR11,AU11,AX11,BA11) -> 0 | BE11: =SUM(D11,G11,J11,M11,P11,S11,V11,Y11,AB11,AE11,AH11,AK11,AN11,AQ11,AT11,AW11,AZ11,BC11) -> 0
D12: 0 | G12: 0 | J12: 0 | M12: 0 | P12: 0 | S12: 0 | V12: 0 | Y12: 0 | AB12: 0 | AE12: 0 | AH12: 0 | AK12: 0 | AN12: 0 | AQ12: 0 | AT12: 0 | AW12: 0 | AZ12: 0 | BC12: 0 | BD12: =SUM(B12,E12,H12,K12,N12,Q12,T12,W12,Z12,AC12,AF12,AI12,AL12,AO12,AR12,AU12,AX12,BA12) -> 0 | BE12: =SUM(D12,G12,J12,M12,P12,S12,V12,Y12,AB12,AE12,AH12,AK12,AN12,AQ12,AT12,AW12,AZ12,BC12) -> 0
D13: 0 | G13: 0 | J13: 0 | M13: 0 | P13: 0 | S13: 0 | V13: 0 | Y13: 0 | AB13: 0 | AE13: 0 | AH13: 0 | AK13: 0 | AN13: 0 | AQ13: 0 | AT13: 0 | AW13: 0 | AZ13: 0 | BC13: 0 | BD13: =SUM(B13,E13,H13,K13,N13,Q13,T13,W13,Z13,AC13,AF13,AI13,AL13,AO13,AR13,AU13,AX13,BA13) -> 0 | BE13: =SUM(D13,G13,J13,M13,P13,S13,V13,Y13,AB13,AE13,AH13,AK13,AN13,AQ13,AT13,AW13,AZ13,BC13) -> 0
D14: 0 | G14: 0 | J14: 0 | M14: 0 | P14: 0 | S14: 0 | V14: 0 | Y14: 0 | AB14: 0 | AE14: 0 | AH14: 0 | AK14: 0 | AN14: 0 | AQ14: 0 | AT14: 0 | AW14: 0 | AZ14: 0 | BC14: 0 | BD14: =SUM(B14,E14,H14,K14,N14,Q14,T14,W14,Z14,AC14,AF14,AI14,AL14,AO14,AR14,AU14,AX14,BA14) -> 0 | BE14: =SUM(D14,G14,J14,M14,P14,S14,V14,Y14,AB14,AE14,AH14,AK14,AN14,AQ14,AT14,AW14,AZ14,BC14) -> 0
A15: SUBTOTAL (all subcontractor/consultant costs) | B15: =SUM(B11:B14) -> 0 | D15: =SUM(D11:D14) -> 0 | E15: =SUM(E11:E14) -> 0 | G15: =SUM(G11:G14) -> 0 | H15: =SUM(H11:H14) -> 0 | J15: =SUM(J11:J14) -> 0 | K15: =SUM(K11:K14) -> 0 | M15: =SUM(M11:M14) -> 0 | N15: =SUM(N11:N14) -> 0 | P15: =SUM(P11:P14) -> 0 | Q15: =SUM(Q11:Q14) -> 0 | S15: =SUM(S11:S14) -> 0 | T15: =SUM(T11:T14) -> 0 | V15: =SUM(V11:V14) -> 0 | W15: =SUM(W11:W14) -> 0 | Y15: =SUM(Y11:Y14) -> 0 | Z15: =SUM(Z11:Z14) -> 0 | AB15: =SUM(AB11:AB14) -> 0 | AC15: =SUM(AC11:AC14) -> 0 | AE15: =SUM(AE11:AE14) -> 0 | AF15: =SUM(AF11:AF14) -> 0 | AH15: =SUM(AH11:AH14) -> 0 | AI15: =SUM(AI11:AI14) -> 0 | AK15: =SUM(AK11:AK14) -> 0 | AL15: =SUM(AL11:AL14) -> 0 | AN15: =SUM(AN11:AN14) -> 0 | AO15: =SUM(AO11:AO14) -> 0 | AQ15: =SUM(AQ11:AQ14) -> 0 | AR15: =SUM(AR11:AR14) -> 0 | AT15: =SUM(AT11:AT14) -> 0 | AU15: =SUM(AU11:AU14) -> 0 | AW15: =SUM(AW11:AW14) -> 0 | AX15: =SUM(AX11:AX14) -> 0 | AZ15: =SUM(AZ11:AZ14) -> 0 | BA15: =SUM(BA11:BA14) -> 0 | BC15: =SUM(BC11:BC14) -> 0 | BD15: =SUM(B15,E15,H15,K15,N15,Q15,T15,W15,Z15,AC15,AF15,AI15,AL15,AO15,AR15,AU15,AX15,BA15) -> 0 | BE15: =SUM(D15,G15,J15,M15,P15,S15,V15,Y15,AB15,AE15,AH15,AK15,AN15,AQ15,AT15,AW15,AZ15,BC15) -> 0
A16: MATERIALS | D16: 0 | G16: 0 | J16: 0 | M16: $ | P16: $ | S16: $ | V16: $ | Y16: $ | AB16: $ | AE16: $ | AH16: $ | AK16: $ | AN16: $ | AQ16: $ | AT16: $ | AW16: $ | AZ16: $ | BC16: $ | BE16: =SUM(D16,G16,J16,M16,P16,S16,V16,Y16,AB16,AE16,AH16,AK16,AN16,AQ16,AT16,AW16,AZ16,BC16) -> 0
A17: EQUIPMENT | D17: 0 | G17: 0 | J17: 0 | M17: 0 | P17: 0 | S17: 0 | V17: 0 | Y17: 0 | AB17: 0 | AE17: 0 | AH17: 0 | AK17: 0 | AN17: 0 | AQ17: 0 | AT17: 0 | AW17: 0 | AZ17: 0 | BC17: 0 | BE17: =SUM(D17,G17,J17,M17,P17,S17,V17,Y17,AB17,AE17,AH17,AK17,AN17,AQ17,AT17,AW17,AZ17,BC17) -> 0
A18: FABRICATION COSTS
A19: TRAVEL | D19: 0 | G19: 0 | J19: 0 | M19: $ | P19: $ | S19: $ | V19: $ | Y19: $ | AB19: $ | AE19: $ | AH19: $ | AK19: $ | AN19: $ | AQ19: $ | AT19: $ | AW19: $ | AZ19: $ | BC19: $ | BE19: =SUM(D19,G19,J19,M19,P19,S19,V19,Y19,AB19,AE19,AH19,AK19,AN19,AQ19,AT19,AW19,AZ19,BC19) -> 0
A20: OTHER DIRECT COSTS (ODCs) 1 | D20: $ | G20: $ | J20: $ | M20: $ | P20: $ | S20: $ | V20: $ | Y20: $ | AB20: $ | AE20: $ | AH20: $ | AK20: $ | AN20: $ | AQ20: $ | AT20: $ | AW20: $ | AZ20: $ | BC20: $ | BE20: =SUM(D20,G20,J20,M20,P20,S20,V20,Y20,AB20,AE20,AH20,AK20,AN20,AQ20,AT20,AW20,AZ20,BC20) -> 0
A21: OTHER DIRECT COSTS (ODCs) 2 | D21: 0 | G21: 0 | J21: 0 | M21: 0 | P21: 0 | S21: 0 | V21: 0 | Y21: 0 | AB21: 0 | AE21: 0 | AH21: 0 | AK21: 0 | AN21: 0 | AQ21: 0 | AT21: 0 | AW21: 0 | AZ21: 0 | BC21: 0 | BE21: =SUM(D21,G21,J21,M21,P21,S21,V21,Y21,AB21,AE21,AH21,AK21,AN21,AQ21,AT21,AW21,AZ21,BC21) -> 0
A22: OTHER DIRECT COSTS (ODCs) 3 | D22: 0 | G22: 0 | J22: 0 | M22: 0 | P22: 0 | S22: 0 | V22: 0 | Y22: 0 | AB22: 0 | AE22: 0 | AH22: 0 | AK22: 0 | AN22: 0 | AQ22: 0 | AT22: 0 | AW22: 0 | AZ22: 0 | BC22: 0 | BE22: =SUM(D22,G22,J22,M22,P22,S22,V22,Y22,AB22,AE22,AH22,AK22,AN22,AQ22,AT22,AW22,AZ22,BC22) -> 0
A23: SUBTOTAL (M&E, Travel, ODCs) | D23: =SUM(D16:D22) -> 0 | G23: =SUM(G16:G22) -> 0 | J23: =SUM(J16:J22) -> 0 | M23: =SUM(M16:M22) -> 0 | P23: =SUM(P16:P22) -> 0 | S23: =SUM(S16:S22) -> 0 | V23: =SUM(V16:V22) -> 0 | Y23: =SUM(Y16:Y22) -> 0 | AB23: =SUM(AB16:AB22) -> 0 | AE23: =SUM(AE16:AE22) -> 0 | AH23: =SUM(AH16:AH22) -> 0 | AK23: =SUM(AK16:AK22) -> 0 | AN23: =SUM(AN16:AN22) -> 0 | AQ23: =SUM(AQ16:AQ22) -> 0 | AT23: =SUM(AT16:AT22) -> 0 | AW23: =SUM(AW16:AW22) -> 0 | AZ23: =SUM(AZ16:AZ22) -> 0 | BC23: =SUM(BC16:BC22) -> 0 | BE23: =SUM(D23,G23,J23,M23,P23,S23,V23,Y23,AB23,AE23,AH23,AK23,AN23,AQ23,AT23,AW23,AZ23,BC23) -> 0
A24: Profit | D24: 0 | G24: 0 | J24: 0 | M24: 0 | P24: 0 | S24: 0 | V24: 0 | Y24: 0 | AB24: 0 | AE24: 0 | AH24: 0 | AK24: 0 | AN24: 0 | AQ24: 0 | AT24: 0 | AW24: 0 | AZ24: 0 | BC24: 0 | BE24: =SUM(D24,G24,J24,M24,P24,S24,V24,Y24,AB24,AE24,AH24,AK24,AN24,AQ24,AT24,AW24,AZ24,BC24) -> 0
A25: TOTAL PRICE | D25: =SUM(D23,D15,D24,D10) -> 0 | G25: =SUM(G23,G15,G24,G10) -> 0 | J25: =SUM(J23,J15,J24,J10) -> 0 | M25: =SUM(M23,M15,M24,M10) -> 0 | P25: =SUM(P23,P15,P24,P10) -> 0 | S25: =SUM(S23,S15,S24,S10) -> 0 | V25: =SUM(V23,V15,V24,V10) -> 0 | Y25: =SUM(Y23,Y15,Y24,Y10) -> 0 | AB25: =SUM(AB23,AB15,AB24,AB10) -> 0 | AE25: =SUM(AE23,AE15,AE24,AE10) -> 0 | AH25: =SUM(AH23,AH15,AH24,AH10) -> 0 | AK25: =SUM(AK23,AK15,AK24,AK10) -> 0 | AN25: =SUM(AN23,AN15,AN24,AN10) -> 0 | AQ25: =SUM(AQ23,AQ15,AQ24,AQ10) -> 0 | AT25: =SUM(AT23,AT15,AT24,AT10) -> 0 | AW25: =SUM(AW23,AW15,AW24,AW10) -> 0 | AZ25: =SUM(AZ23,AZ15,AZ24,AZ10) -> 0 | BC25: =SUM(BC23,BC15,BC24,BC10) -> 0 | BE25: =SUM(D25,G25,J25,M25,P25,S25,V25,Y25,AB25,AE25,AH25,AK25,AN25,AQ25,AT25,AW25,AZ25,BC25) -> 0
A26: GOVERNMENT SHARE | D26: 0 | G26: 0 | J26: 0 | M26: 0 | P26: 0 | S26: 0 | V26: 0 | Y26: 0 | AB26: 0 | AE26: 0 | AH26: 0 | AK26: 0 | AN26: 0 | AQ26: 0 | AT26: 0 | AW26: 0 | AZ26: 0 | BC26: 0 | BE26: =SUM(D26,G26,J26,M26,P26,S26,V26,Y26,AB26,AE26,AH26,AK26,AN26,AQ26,AT26,AW26,AZ26,BC26) -> 0
A27: RECIPIENT SHARE (if applicable) | D27: =D25-D26 -> 0 | G27: =G25-G26 -> 0 | J27: =J25-J26 -> 0 | M27: =M25-M26 -> 0 | P27: =P25-P26 -> 0 | S27: =S25-S26 -> 0 | V27: =V25-V26 -> 0 | Y27: =Y25-Y26 -> 0 | AB27: =AB25-AB26 -> 0 | AE27: =AE25-AE26 -> 0 | AH27: =AH25-AH26 -> 0 | AK27: =AK25-AK26 -> 0 | AN27: =AN25-AN26 -> 0 | AQ27: =AQ25-AQ26 -> 0 | AT27: =AT25-AT26 -> 0 | AW27: =AW25-AW26 -> 0 | AZ27: =AZ25-AZ26 -> 0 | BC27: =BC25-BC26 -> 0 | BE27: =SUM(D27,G27,J27,M27,P27,S27,V27,Y27,AB27,AE27,AH27,AK27,AN27,AQ27,AT27,AW27,AZ27,BC27) -> 0
B29: Gov't Share | C29: Performer Share | D29: Total Project Cost
A30: Phase 2 Total | B30: =BE26 -> 0 | C30: =BE27 -> 0 | D30: =SUM(B30,C30) -> 0
A32: 1. Proposers are required to add in the Phase 2 cost in the cells above
A33: 2. Phase 2 period of performance are stipulated in the PS and above.
A34: ='Phase 1- Budget by Month'!A33 -> 3. Each submission shall include a separate Price Summary spreadsheet for the Prime and each subcontractor.
A35: ='Phase 1- Budget by Month'!A34 -> 4. Rows can be added to reflect labor categories, subcontractors/consultants, and additional ODCs, as necessary. However, none of the fields currently in the template should be removed, to include formulas.
A36: ='Phase 1- Budget by Month'!A35 -> 5. All proposers, to include Institutions of Higher Education, must include labor hours and associated labor rates for each labor category as stipulated above. Proposers are prohibited from using percent level of effort (LOE) calculations.
A37: ='Phase 1- Budget by Month'!A36 -> 6. Cost elements above should be fully burdened, inclusive of all applicable indirect costs and fee, if applcable. Visibility into indirect rates/costs is not required. Proposers may submit supporting or clarifying information regarding direct and indirect rates in Volume 2.
A38: ='Phase 1- Budget by Month'!A37 -> 7. The pricing for this program must be presented using the 18-month format above. Do not add additional months.
